vis2048/__init__.py
vis2048/demo.py
vis2048/game.py
vis2048/mat.py
vis2048/vec2.py
vis2048/vis.py
vis2048-1.0.3.dist-info/LICENSE
vis2048-1.0.3.dist-info/METADATA
vis2048-1.0.3.dist-info/WHEEL
vis2048-1.0.3.dist-info/top_level.txt
vis2048-1.0.3.dist-info/RECORD
