Metadata-Version: 2.1
Name: vis2048
Version: 1.0.3
Summary: Implementation of 2048 with visualization support
Home-page: https://github.com/Fylipp/vis2048
Author: Philipp Ploder
License: UNKNOWN
Keywords: 2048 visualization
Platform: UNKNOWN
Classifier: Development Status :: 5 - Production/Stable
Classifier: License :: OSI Approved :: MIT License
Classifier: Programming Language :: Python :: 3
